rebecca.repository-0.4-py2.7-nspkg.pth
rebecca/repository/config.py
rebecca/repository/decorators.py
rebecca/repository/fs.py
rebecca/repository/interfaces.py
rebecca/repository/sqla.py
rebecca/repository/__init__.py
rebecca.repository-0.4.dist-info/DESCRIPTION.rst
rebecca.repository-0.4.dist-info/entry_points.txt
rebecca.repository-0.4.dist-info/METADATA
rebecca.repository-0.4.dist-info/namespace_packages.txt
rebecca.repository-0.4.dist-info/pydist.json
rebecca.repository-0.4.dist-info/RECORD
rebecca.repository-0.4.dist-info/top_level.txt
rebecca.repository-0.4.dist-info/WHEEL
