Metadata-Version: 2.0
Name: rebecca.repository
Version: 0.4
Summary: helper utility for repository pattern of PofEAA
Home-page: https://github.com/rebeccaframework/rebecca.repository
Author: Atsushi Odagiri
Author-email: aodagx@gmail.com
License: MIT
Platform: UNKNOWN
Classifier: Programming Language :: Python
Classifier: Programming Language :: Python :: 2.7
Classifier: Programming Language :: Python :: 3
Classifier: Programming Language :: Python :: 3.3
Classifier: Framework :: Pyramid
Requires-Dist: setuptools
Requires-Dist: zope.interface
Requires-Dist: six
Provides-Extra: sqlalchemy
Requires-Dist: sqlalchemy; extra == 'sqlalchemy'
Provides-Extra: testing
Requires-Dist: pytest; extra == 'testing'
Requires-Dist: pytest-cov; extra == 'testing'
Requires-Dist: coverage; extra == 'testing'
Requires-Dist: testfixtures; extra == 'testing'
Requires-Dist: pyramid; extra == 'testing'
Provides-Extra: pyramid
Requires-Dist: pyramid; extra == 'pyramid'
Provides-Extra: fs
Requires-Dist: repoze.filesafe; extra == 'fs'
Provides-Extra: dev
Requires-Dist: docutils; extra == 'dev'
